rxlm/__init__.py
rxlm/compile.py
rxlm/experimental/__init__.py
rxlm/experimental/attention.py
rxlm/experimental/md_gdn/__init__.py
rxlm/experimental/md_gdn/layer.py
rxlm/experimental/models.py
rxlm/experimental/moe.py
rxlm/llm/__init__.py
rxlm/llm/models.py
rxlm/llm_training/__init__.py
rxlm/llm_training/dataset.py
rxlm/llm_training/models.py
rxlm/llm_training/supervised.py
rxlm/memory/__init__.py
rxlm/memory/attention.py
rxlm/memory/gate.py
rxlm/memory/norm.py
rxlm/memory/stm.py
rxlm/metrics/__init__.py
rxlm/metrics/tensorbleu.py
rxlm/mrq_bench/__init__.py
rxlm/mrq_bench/benchmark.py
rxlm/mrq_bench/dataset.py
rxlm/mrq_bench/models.py
rxlm/mrq_bench/sampler.py
rxlm/mrq_bench/score.py
rxlm/rxt/__init__.py
rxlm/rxt/models.py
rxlm/training/__init__.py
rxlm/training/base.py
rxlm/training/bml.py
rxlm/training/callbacks.py
rxlm/training/dataset.py
rxlm/training/ddp.py
rxlm/training/models.py
rxlm/training/mrl.py
rxlm/training/optim.py
rxlm/training/reward.py
rxlm/training/rl.py
rxlm/training/scheduler.py
rxlm/training/smst.py
rxlm/training/tokenizer.py
rxlm/training/utils.py
rxlm/transformers/__init__.py
rxlm/transformers/attention.py
rxlm/transformers/ff.py
rxlm/transformers/layers.py
rxlm/transformers/llm_layers.py
rxlm/transformers/llm_models.py
rxlm/transformers/mask.py
rxlm/transformers/models.py
rxlm/transformers/moe.py
rxlm/transformers/positional.py
rxlm/transformers/sampler.py
rxlm/utils.py
rxlm-0.3.58.dist-info/METADATA
rxlm-0.3.58.dist-info/WHEEL
rxlm-0.3.58.dist-info/licenses/LICENSE
rxlm-0.3.58.dist-info/licenses/MODELS_LICENSE
rxlm-0.3.58.dist-info/RECORD
