Metadata-Version: 2.4
Name: rxlm
Version: 0.3.58
Summary: RxNN - RxLM: Reactive Language Models platform
License-File: LICENSE
License-File: MODELS_LICENSE
Keywords: deep-learning,ai,machine-learning,natural-language-processing,nlp,agi,memory-system
Author: Adam Filipek
Author-email: adamfilipek@rxai.dev
Requires-Python: >=3.10
Classifier: Programming Language :: Python :: 3
Classifier: Programming Language :: Python :: 3.10
Classifier: Programming Language :: Python :: 3.11
Classifier: Programming Language :: Python :: 3.12
Classifier: Programming Language :: Python :: 3.13
Classifier: Programming Language :: Python :: 3.14
Requires-Dist: datasets (>=3.5.0,<4.0.0)
Requires-Dist: huggingface-hub (>=0.30.0,<0.31.0)
Requires-Dist: nltk (>=3.9.1,<4.0.0)
Requires-Dist: scikit-learn (>=1.7.2,<2.0.0)
Requires-Dist: tensorboard (>=2.19.0,<3.0.0)
Requires-Dist: tokenizers (>=0.21.0,<0.22.0)
Requires-Dist: torch (>=2.8.0,<3.0.0)
Requires-Dist: transformer-engine (>=2.8.0,<3.0.0)
Requires-Dist: transformers (>=4.51.0,<5.0.0)
Project-URL: Homepage, https://rxai.dev/rxnn
Project-URL: Repository, https://github.com/RxAI-dev/rxlm
